setup.py
bin/edsmodule
edsmodule/__init__.py
edsmodule.egg-info/PKG-INFO
edsmodule.egg-info/SOURCES.txt
edsmodule.egg-info/dependency_links.txt
edsmodule.egg-info/requires.txt
edsmodule.egg-info/top_level.txt