Metadata-Version: 1.0
Name: edsmodule
Version: 0.1.3
Summary: the tool for export or import modules of datacanvas eds service
Home-page: http://xiaoh.me
Author: xiaoh
Author-email: xiaoh@about.me
License: MIT Licence
Keywords: eds,datacanvas,xiaoh,module,ehc,aps
Platform: any
